bc_semgrep-1.7.2.data/purelib/semdep/__init__.py
bc_semgrep-1.7.2.data/purelib/semdep/find_lockfiles.py
bc_semgrep-1.7.2.data/purelib/semdep/package_restrictions.py
bc_semgrep-1.7.2.data/purelib/semdep/parse_lockfile.py
bc_semgrep-1.7.2.data/purelib/semdep/parsers/__init__.py
bc_semgrep-1.7.2.data/purelib/semdep/parsers/gem.py
bc_semgrep-1.7.2.data/purelib/semdep/parsers/go_sum.py
bc_semgrep-1.7.2.data/purelib/semdep/parsers/gradle.py
bc_semgrep-1.7.2.data/purelib/semdep/parsers/package_lock.py
bc_semgrep-1.7.2.data/purelib/semdep/parsers/pipfile.py
bc_semgrep-1.7.2.data/purelib/semdep/parsers/poetry.py
bc_semgrep-1.7.2.data/purelib/semdep/parsers/pom_tree.py
bc_semgrep-1.7.2.data/purelib/semdep/parsers/requirements.py
bc_semgrep-1.7.2.data/purelib/semdep/parsers/util.py
bc_semgrep-1.7.2.data/purelib/semdep/parsers/yarn.py
bc_semgrep-1.7.2.data/purelib/semgrep/__init__.py
bc_semgrep-1.7.2.data/purelib/semgrep/__main__.py
bc_semgrep-1.7.2.data/purelib/semgrep/autofix.py
bc_semgrep-1.7.2.data/purelib/semgrep/bytesize.py
bc_semgrep-1.7.2.data/purelib/semgrep/cli.py
bc_semgrep-1.7.2.data/purelib/semgrep/config_resolver.py
bc_semgrep-1.7.2.data/purelib/semgrep/constants.py
bc_semgrep-1.7.2.data/purelib/semgrep/core_output.py
bc_semgrep-1.7.2.data/purelib/semgrep/core_runner.py
bc_semgrep-1.7.2.data/purelib/semgrep/default_group.py
bc_semgrep-1.7.2.data/purelib/semgrep/dependency_aware_rule.py
bc_semgrep-1.7.2.data/purelib/semgrep/dump_ast.py
bc_semgrep-1.7.2.data/purelib/semgrep/env.py
bc_semgrep-1.7.2.data/purelib/semgrep/error.py
bc_semgrep-1.7.2.data/purelib/semgrep/error_handler.py
bc_semgrep-1.7.2.data/purelib/semgrep/exclude_rules.py
bc_semgrep-1.7.2.data/purelib/semgrep/fork_subprocess.py
bc_semgrep-1.7.2.data/purelib/semgrep/git.py
bc_semgrep-1.7.2.data/purelib/semgrep/ignores.py
bc_semgrep-1.7.2.data/purelib/semgrep/join_rule.py
bc_semgrep-1.7.2.data/purelib/semgrep/meta.py
bc_semgrep-1.7.2.data/purelib/semgrep/metrics.py
bc_semgrep-1.7.2.dist-info/LICENSE
bc_semgrep-1.7.2.dist-info/METADATA
bc_semgrep-1.7.2.dist-info/WHEEL
bc_semgrep-1.7.2.dist-info/entry_points.txt
bc_semgrep-1.7.2.dist-info/top_level.txt
bc_semgrep-1.7.2.dist-info/RECORD
