Metadata-Version: 2.1
Name: bc-semgrep
Version: 1.7.2
Summary: Lightweight static analysis for many languages. Find bug variants with patterns that look like source code.
Home-page: https://github.com/bridgecrewio/semgrep
Author: Return To Corporation
Author-email: support@r2c.dev
License: UNKNOWN
Platform: UNKNOWN
Classifier: Environment :: Console
Classifier: License :: OSI Approved :: GNU Lesser General Public License v2 (LGPLv2)
Classifier: Operating System :: MacOS
Classifier: Operating System :: POSIX :: Linux
Classifier: Programming Language :: Python :: 3.7
Classifier: Programming Language :: Python :: 3.8
Classifier: Programming Language :: Python :: 3.9
Classifier: Topic :: Security
Classifier: Topic :: Software Development :: Quality Assurance
Requires-Python: >=3.7
Requires-Dist: attrs (>=21.3)
Requires-Dist: boltons (~=21.0)
Requires-Dist: colorama (~=0.4.0)
Requires-Dist: click (~=8.1)
Requires-Dist: click-option-group (~=0.5)
Requires-Dist: glom (~=22.1)
Requires-Dist: requests (~=2.22)
Requires-Dist: ruamel.yaml (<0.18,>=0.16.0)
Requires-Dist: tqdm (~=4.46)
Requires-Dist: packaging (~=21.0)
Requires-Dist: jsonschema (~=4.6)
Requires-Dist: wcmatch (~=8.3)
Requires-Dist: peewee (~=3.14)
Requires-Dist: defusedxml (~=0.7.1)
Requires-Dist: urllib3 (~=1.26)
Requires-Dist: typing-extensions (~=4.2)
Requires-Dist: python-lsp-jsonrpc (~=1.0.0)
Requires-Dist: tomli (~=2.0.1)
Requires-Dist: parsy (~=2.0)
Provides-Extra: experiments
Requires-Dist: jsonnet (~=0.18) ; extra == 'experiments'
